foydalidasturlar/__init__.py
foydalidasturlar/email.py
foydalidasturlar/karta.py
foydalidasturlar/manzil.py
foydalidasturlar/parol.py
foydalidasturlar/shaxs.py
foydalidasturlar/telefon.py
foydalidasturlar/utils.py
foydalidasturlar-1.0.0.dist-info/LICENSE
foydalidasturlar-1.0.0.dist-info/METADATA
foydalidasturlar-1.0.0.dist-info/WHEEL
foydalidasturlar-1.0.0.dist-info/top_level.txt
foydalidasturlar-1.0.0.dist-info/RECORD
