Metadata-Version: 2.1
Name: foydalidasturlar
Version: 1.0.0
Summary: Turli xil tasodifiy ma'lumotlar generatori
Home-page: https://github.com/sizning_username/foydalidasturlar
Author: Sizning ismingiz
Author-email: sizning_emailingiz@gmail.com
Keywords: generator,fake data,random,uzbekistan,test data
Classifier: Programming Language :: Python :: 3
Classifier: License :: OSI Approved :: MIT License
Classifier: Operating System :: OS Independent
Classifier: Development Status :: 4 - Beta
Classifier: Intended Audience :: Developers
Classifier: Topic :: Software Development :: Libraries :: Python Modules
Requires-Python: >=3.6
License-File: LICENSE
